xindi-lib/xindi.py
xindilib/xindi.py
xindi_lib-0.1.2.dist-info/METADATA
xindi_lib-0.1.2.dist-info/WHEEL
xindi_lib-0.1.2.dist-info/top_level.txt
xindi_lib-0.1.2.dist-info/RECORD
