Metadata-Version: 2.1
Name: xindi-lib
Version: 0.1.2
Summary: library to manage ip subnets
Home-page: https://github.com/wolfbo/xindi-lib
Author: Wolfgang Wangerin
Author-email: wolfgang.wangerin@budohh.de
License: MIT
Platform: UNKNOWN
Classifier: License :: OSI Approved :: MIT License
Classifier: Programming Language :: Python
Classifier: Programming Language :: Python :: 3
Requires-Dist: ipaddress
